98SkillTest2Prep/Skiltest_2025/skilltest2_to_student/P2/asyncrx.v
////////////////////////////////////////////////////////
module async_receiver(
    input clk,
    input RxD,
    output reg RxD_data_ready = 0,
    output reg [7:0] RxD_data = 0,  // data received, valid only (for one clock cycle) when RxD_data_ready is asserted

    // We also detect if a gap occurs in the received stream of characters
    // That can be useful if multiple characters are sent in burst
    //  so that multiple characters can be treated as a "packet"
    output RxD_idle,  // asserted when no data has been received for a while
    output reg RxD_endofpacket = 0  // asserted for one clock cycle when a packet has been detected (i.e. RxD_idle is going high)
);

parameter ClkFrequency = 25000000; // 25MHz
parameter Baud = 115200;

parameter Oversampling = 8;  // needs to be a power of 2
// we oversample the RxD line at a fixed rate to capture each RxD data bit at the "right" time
// 8 times oversampling by default, use 16 for higher quality reception

generate
    if(ClkFrequency<Baud*Oversampling) ASSERTION_ERROR PARAMETER_OUT_OF_RANGE("Frequency too low for current Baud rate and oversampling");
    if(Oversampling<8 || ((Oversampling & (Oversampling-1))!=0)) ASSERTION_ERROR PARAMETER_OUT_OF_RANGE("Invalid oversampling value");
endgenerate

////////////////////////////////
reg [3:0] RxD_state = 0;

wire OversamplingTick;
BaudTickGen #(ClkFrequency, Baud, Oversampling) tickgen(.clk(clk), .enable(1'b1), .tick(OversamplingTick));

// synchronize RxD to our clk domain
reg [1:0] RxD_sync = 2'b11;
always @(posedge clk) if(OversamplingTick) RxD_sync <= {RxD_sync[0], RxD};

// and filter it
reg [1:0] Filter_cnt = 2'b11;
reg RxD_bit = 1'b1;

always @(posedge clk)
if(OversamplingTick)
begin
    if(RxD_sync[1]==1'b1 && Filter_cnt!=2'b11) Filter_cnt <= Filter_cnt + 1'd1;
    else
    if(RxD_sync[1]==1'b0 && Filter_cnt!=2'b00) Filter_cnt <= Filter_cnt - 1'd1;

    if(Filter_cnt==2'b11) RxD_bit <= 1'b1;
    else
    if(Filter_cnt==2'b00) RxD_bit <= 1'b0;
end

// and decide when is the good time to sample the RxD line
function integer log2(input integer v); begin log2=0; while(v>>log2) log2=log2+1; end endfunction
localparam l2o = log2(Oversampling);
reg [l2o-2:0] OversamplingCnt = 0;
always @(posedge clk) if(OversamplingTick) OversamplingCnt <= (RxD_state==0) ? 1'd0 : OversamplingCnt + 1'd1;
wire sampleNow = OversamplingTick && (OversamplingCnt == Oversampling / 2);

// now we can accumulate the RxD bits in a shift-register
always @(posedge clk)
case(RxD_state)
    4'b0000: if(~RxD_bit) RxD_state <= 4'b0001;  // start bit found?
    4'b0001: if(sampleNow) RxD_state <= 4'b1000;  // sync start bit to sampleNow
    4'b1000: if(sampleNow) RxD_state <= 4'b1001;  // bit 0
    4'b1001: if(sampleNow) RxD_state <= 4'b1010;  // bit 1
    4'b1010: if(sampleNow) RxD_state <= 4'b1011;  // bit 2
    4'b1011: if(sampleNow) RxD_state <= 4'b1100;  // bit 3
    4'b1100: if(sampleNow) RxD_state <= 4'b1101;  // bit 4
    4'b1101: if(sampleNow) RxD_state <= 4'b1110;  // bit 5
    4'b1110: if(sampleNow) RxD_state <= 4'b1111;  // bit 6
    4'b1111: if(sampleNow) RxD_state <= 4'b0010;  // bit 7
    4'b0010: if(sampleNow) RxD_state <= 4'b0000;  // stop bit
    default: RxD_state <= 4'b0000;
endcase

always @(posedge clk)
if(sampleNow && RxD_state[3]) RxD_data <= {RxD_bit, RxD_data[7:1]};

//reg RxD_data_error = 0;
always @(posedge clk)
begin
    RxD_data_ready <= (sampleNow && RxD_state==4'b0010 && RxD_bit);  // make sure a stop bit is received
    //RxD_data_error <= (sampleNow && RxD_state==4'b0010 && ~RxD_bit);  // error if a stop bit is not received
end

reg [l2o+1:0] GapCnt = 0;
always @(posedge clk) if (RxD_state!=0) GapCnt<=0; else if(OversamplingTick & ~GapCnt[log2(Oversampling)+1]) GapCnt <= GapCnt + 1'h1;
assign RxD_idle = GapCnt[l2o+1];
always @(posedge clk) RxD_endofpacket <= OversamplingTick & ~GapCnt[l2o+1] & &GapCnt[l2o:0];

endmodule


////////////////////////////////////////////////////////
// dummy module used to be able to raise an assertion in Verilog
module ASSERTION_ERROR();
endmodule


////////////////////////////////////////////////////////
module BaudTickGen(
    input clk, enable,
    output tick  // generate a tick at the specified baud rate * oversampling
);
parameter ClkFrequency = 25000000;
parameter Baud = 115200;
parameter Oversampling = 1;

function integer log2(input integer v); begin log2=0; while(v>>log2) log2=log2+1; end endfunction
localparam AccWidth = log2(ClkFrequency/Baud)+8;  // +/- 2% max timing error over a byte
reg [AccWidth:0] Acc = 0;
localparam ShiftLimiter = log2(Baud*Oversampling >> (31-AccWidth));  // this makes sure Inc calculation doesn't overflow
localparam Inc = ((Baud*Oversampling << (AccWidth-ShiftLimiter))+(ClkFrequency>>(ShiftLimiter+1)))/(ClkFrequency>>ShiftLimiter);
always @(posedge clk) if(enable) Acc <= Acc[AccWidth-1:0] + Inc[AccWidth:0]; else Acc <= Inc[AccWidth:0];
assign tick = Acc[AccWidth];
endmodule


////////////////////////////////////////////////////////

98SkillTest2Prep/Skiltest_2025/skilltest2_to_student/P2/cocotb/TB1/async_receiver_tb.v
module async_receiver_tb (
    input clk,
    input RxD,  // UART Tx line from testbench -> DUT Rx
    output RxD_data_ready,
    output [7:0] RxD_data,
    output RxD_idle,
    output RxD_endofpacket
);
  // UART Parameters
  localparam BitDelayNs = 1000000000 / 115200;  // Bit delay in ns (for 115200 baud rate)
  // Parameters
  localparam ClkFrequency = 25000000;  // 25MHz
  localparam Baud = 115200;
  localparam Oversampling = 16;  // Must match the DUT setting

  async_receiver #(
      .ClkFrequency(ClkFrequency),
      .Baud(Baud),
      .Oversampling(Oversampling)
  ) DUT (
      .clk(clk),
      .RxD(RxD),  // Connect TB Tx to DUT Rx
      .RxD_data_ready(RxD_data_ready),
      .RxD_data(RxD_data),
      .RxD_idle(RxD_idle),
      .RxD_endofpacket(RxD_endofpacket)
  );

`ifdef COCOTB_SIM
  initial begin
    $dumpfile("waveform.vcd");  // Name of the dump file
    $dumpvars(0, async_receiver_tb);  // Dump all variables for the top module
  end
`endif
endmodule

98SkillTest2Prep/Skiltest_2025/skilltest2_to_student/P2/cocotb/TB1/waveform.vcd
$date
	Thu Apr 09 13:28:14 2026
$end
$version
	Icarus Verilog
$end
$timescale
	1ps
$end
$scope module async_receiver_tb $end
$var wire 1 ! RxD $end
$var wire 1 " clk $end
$var wire 1 # RxD_idle $end
$var wire 1 $ RxD_endofpacket $end
$var wire 1 % RxD_data_ready $end
$var wire 8 & RxD_data [7:0] $end
$var parameter 32 ' Baud $end
$var parameter 32 ( BitDelayNs $end
$var parameter 32 ) ClkFrequency $end
$var parameter 32 * Oversampling $end
$scope module DUT $end
$var wire 1 ! RxD $end
$var wire 1 " clk $end
$var wire 1 + sampleNow $end
$var wire 1 # RxD_idle $end
$var wire 1 , OversamplingTick $end
$var parameter 32 - Baud $end
$var parameter 32 . ClkFrequency $end
$var parameter 32 / Oversampling $end
$var parameter 32 0 l2o $end
$var reg 2 1 Filter_cnt [1:0] $end
$var reg 7 2 GapCnt [6:0] $end
$var reg 4 3 OversamplingCnt [3:0] $end
$var reg 1 4 RxD_bit $end
$var reg 8 5 RxD_data [7:0] $end
$var reg 1 % RxD_data_ready $end
$var reg 1 $ RxD_endofpacket $end
$var reg 4 6 RxD_state [3:0] $end
$var reg 2 7 RxD_sync [1:0] $end
$scope function log2 $end
$var integer 32 8 v [31:0] $end
$upscope $end
$scope module tickgen $end
$var wire 1 " clk $end
$var wire 1 9 enable $end
$var wire 1 , tick $end
$var parameter 33 : AccWidth $end
$var parameter 32 ; Baud $end
$var parameter 32 < ClkFrequency $end
$var parameter 33 = Inc $end
$var parameter 32 > Oversampling $end
$var parameter 32 ? ShiftLimiter $end
$var reg 17 @ Acc [16:0] $end
$scope function log2 $end
$var integer 32 A v [31:0] $end
$upscope $end
$upscope $end
$upscope $end
$upscope $end
$enddefinitions $end
$comment Show the parameter values. $end
$dumpall
b110 ?
b10000 >
b1001011100000 =
b1011111010111100001000000 <
b11100001000000000 ;
b10000 :
b101 0
b10000 /
b1011111010111100001000000 .
b11100001000000000 -
b10000 *
b1011111010111100001000000 )
b10000111101000 (
b11100001000000000 '
$end
#0
$dumpvars
bx A
b1001011100000 @
19
b10000 8
b11 7
b0 6
b0 5
14
b0 3
b0 2
b11 1
0,
0+
b0 &
0%
0$
0#
1"
1!
$end
#20000
0"
#40000
b10010111000000 @
1"
#60000
0"
#80000
b11100010100000 @
1"
#100000
0"
#120000
b100101110000000 @
1"
#140000
0"
#160000
b101111001100000 @
1"
#180000
0"
#200000
b111000101000000 @
1"
#220000
0"
#240000
b1000010000100000 @
1"
#260000
0"
#280000
b1001011100000000 @
1"
#300000
0"
#320000
b1010100111100000 @
1"
#340000
0"
#360000
b1011110011000000 @
1"
#380000
0"
#400000
b1100111110100000 @
1"
#420000
0"
#440000
b1110001010000000 @
1"
#460000
0"
#480000
b1111010101100000 @
1"
#500000
0"
#520000
1,
b10000100001000000 @
1"
#540000
0"
#560000
0,
b1101100100000 @
b1 2
1"
#580000
0"
#600000
b10111000000000 @
1"
#620000
0"
#640000
b100000011100000 @
1"
#660000
0"
#680000
b101001111000000 @
1"
#700000
0"
#720000
b110011010100000 @
1"
#740000
0"
#760000
b111100110000000 @
1"
#780000
0"
#800000
b1000110001100000 @
1"
#820000
0"
#840000
b1001111101000000 @
1"
#860000
0"
#880000
b1011001000100000 @
1"
#900000
0"
#920000
b1100010100000000 @
1"
#940000
0"
#960000
b1101011111100000 @
1"
#980000
0"
#1000000
b1110101011000000 @
1"
#1020000
0"
#1040000
b1111110110100000 @
1"
#1060000
0"
#1080000
1,
b10001000010000000 @
1"
#1100000
0"
#1120000
0,
b10001101100000 @
b10 2
1"
#1140000
0"
#1160000
b11011001000000 @
1"
#1180000
0"
#1200000
b100100100100000 @
1"
#1220000
0"
#1240000
b101110000000000 @
1"
#1260000
0"
#1280000
b110111011100000 @
1"
#1300000
0"
#1320000
b1000000111000000 @
1"
#1340000
0"
#1360000
b1001010010100000 @
1"
#1380000
0"
#1400000
b1010011110000000 @
1"
#1420000
0"
#1440000
b1011101001100000 @
1"
#1460000
0"
#1480000
b1100110101000000 @
1"
#1500000
0"
#1520000
b1110000000100000 @
1"
#1540000
0"
#1560000
b1111001100000000 @
1"
#1580000
0"
#1600000
1,
b10000010111100000 @
1"
#1620000
0"
#1640000
0,
b11 2
b1100011000000 @
1"
#1660000
0"
#1680000
b10101110100000 @
1"
#1700000
0"
#1720000
b11111010000000 @
1"
#1740000
0"
#1760000
b101000101100000 @
1"
#1780000
0"
#1800000
b110010001000000 @
1"
#1820000
0"
#1840000
b111011100100000 @
1"
#1860000
0"
#1880000
b1000101000000000 @
1"
#1900000
0"
#1920000
b1001110011100000 @
1"
#1940000
0"
#1960000
b1010111111000000 @
1"
#1980000
0"
#2000000
b1100001010100000 @
1"
0!
#2020000
0"
#2040000
b1101010110000000 @
1"
#2060000
0"
#2080000
b1110100001100000 @
1"
#2100000
0"
#2120000
b1111101101000000 @
1"
#2140000
0"
#2160000
1,
b10000111000100000 @
1"
#2180000
0"
#2200000
0,
b100 2
b10 7
b10000100000000 @
1"
#2220000
0"
#2240000
b11001111100000 @
1"
#2260000
0"
#2280000
b100011011000000 @
1"
#2300000
0"
#2320000
b101100110100000 @
1"
#2340000
0"
#2360000
b110110010000000 @
1"
#2380000
0"
#2400000
b111111101100000 @
1"
#2420000
0"
#2440000
b1001001001000000 @
1"
#2460000
0"
#2480000
b1010010100100000 @
1"
#2500000
0"
#2520000
b1011100000000000 @
1"
#2540000
0"
#2560000
b1100101011100000 @
1"
#2580000
0"
#2600000
b1101110111000000 @
1"
#2620000
0"
#2640000
b1111000010100000 @
1"
#2660000
0"
#2680000
1,
b10000001110000000 @
1"
#2700000
0"
#2720000
0,
b1011001100000 @
b0 7
b101 2
1"
#2740000
0"
#2760000
b10100101000000 @
1"
#2780000
0"
#2800000
b11110000100000 @
1"
#2820000
0"
#2840000
b100111100000000 @
1"
#2860000
0"
#2880000
b110000111100000 @
1"
#2900000
0"
#2920000
b111010011000000 @
1"
#2940000
0"
#2960000
b1000011110100000 @
1"
#2980000
0"
#3000000
b1001101010000000 @
1"
#3020000
0"
#3040000
b1010110101100000 @
1"
#3060000
0"
#3080000
b1100000001000000 @
1"
#3100000
0"
#3120000
b1101001100100000 @
1"
#3140000
0"
#3160000
b1110011000000000 @
1"
#3180000
0"
#3200000
b1111100011100000 @
1"
#3220000
0"
#3240000
1,
b10000101111000000 @
1"
#3260000
0"
#3280000
0,
b1111010100000 @
b10 1
b110 2
1"
#3300000
0"
#3320000
b11000110000000 @
1"
#3340000
0"
#3360000
b100010001100000 @
1"
#3380000
0"
#3400000
b101011101000000 @
1"
#3420000
0"
#3440000
b110101000100000 @
1"
#3460000
0"
#3480000
b111110100000000 @
1"
#3500000
0"
#3520000
b1000111111100000 @
1"
#3540000
0"
#3560000
b1010001011000000 @
1"
#3580000
0"
#3600000
b1011010110100000 @
1"
#3620000
0"
#3640000
b1100100010000000 @
1"
#3660000
0"
#3680000
b1101101101100000 @
1"
#3700000
0"
#3720000
b1110111001000000 @
1"
#3740000
0"
#3760000
1,
b10000000100100000 @
1"
#3780000
0"
#3800000
0,
b111 2
b1 1
b1010000000000 @
1"
#3820000
0"
#3840000
b10011011100000 @
1"
#3860000
0"
#3880000
b11100111000000 @
1"
#3900000
0"
#3920000
b100110010100000 @
1"
#3940000
0"
#3960000
b101111110000000 @
1"
#3980000
0"
#4000000
b111001001100000 @
1"
#4020000
0"
#4040000
b1000010101000000 @
1"
#4060000
0"
#4080000
b1001100000100000 @
1"
#4100000
0"
#4120000
b1010101100000000 @
1"
#4140000
0"
#4160000
b1011110111100000 @
1"
#4180000
0"
#4200000
b1101000011000000 @
1"
#4220000
0"
#4240000
b1110001110100000 @
1"
#4260000
0"
#4280000
b1111011010000000 @
1"
#4300000
0"
#4320000
1,
b10000100101100000 @
1"
#4340000
0"
#4360000
0,
b1000 2
b0 1
b1110001000000 @
1"
#4380000
0"
#4400000
b10111100100000 @
1"
#4420000
0"
#4440000
b100001000000000 @
1"
#4460000
0"
#4480000
b101010011100000 @
1"
#4500000
0"
#4520000
b110011111000000 @
1"
#4540000
0"
#4560000
b111101010100000 @
1"
#4580000
0"
#4600000
b1000110110000000 @
1"
#4620000
0"
#4640000
b1010000001100000 @
1"
#4660000
0"
#4680000
b1011001101000000 @
1"
#4700000
0"
#4720000
b1100011000100000 @
1"
#4740000
0"
#4760000
b1101100100000000 @
1"
#4780000
0"
#4800000
b1110101111100000 @
1"
#4820000
0"
#4840000
b1111111011000000 @
1"
#4860000
0"
#4880000
1,
b10001000110100000 @
1"
#4900000
0"
#4920000
0,
b1001 2
04
b10010010000000 @
1"
#4940000
0"
#4960000
b11011101100000 @
b1 6
1"
#4980000
0"
#5000000
b0 2
b100101001000000 @
1"
#5020000
0"
#5040000
b101110100100000 @
1"
#5060000
0"
#5080000
b111000000000000 @
1"
#5100000
0"
#5120000
b1000001011100000 @
1"
#5140000
0"
#5160000
b1001010111000000 @
1"
#5180000
0"
#5200000
b1010100010100000 @
1"
#5220000
0"
#5240000
b1011101110000000 @
1"
#5260000
0"
#5280000
b1100111001100000 @
1"
#5300000
0"
#5320000
b1110000101000000 @
1"
#5340000
0"
#5360000
b1111010000100000 @
1"
#5380000
0"
#5400000
1,
b10000011100000000 @
1"
#5420000
0"
#5440000
0,
b1100111100000 @
b1 3
1"
#5460000
0"
#5480000
b10110011000000 @
1"
#5500000
0"
#5520000
b11111110100000 @
1"
#5540000
0"
#5560000
b101001010000000 @
1"
#5580000
0"
#5600000
b110010101100000 @
1"
#5620000
0"
#5640000
b111100001000000 @
1"
#5660000
0"
#5680000
b1000101100100000 @
1"
#5700000
0"
#5720000
b1001111000000000 @
1"
#5740000
0"
#5760000
b1011000011100000 @
1"
#5780000
0"
#5800000
b1100001111000000 @
1"
#5820000
0"
#5840000
b1101011010100000 @
1"
#5860000
0"
#5880000
b1110100110000000 @
1"
#5900000
0"
#5920000
b1111110001100000 @
1"
#5940000
0"
#5960000
1,
b10000111101000000 @
1"
#5980000
0"
#6000000
0,
b10001000100000 @
b10 3
1"
#6020000
0"
#6040000
b11010100000000 @
1"
#6060000
0"
#6080000
b100011111100000 @
1"
#6100000
0"
#6120000
b101101011000000 @
1"
#6140000
0"
#6160000
b110110110100000 @
1"
#6180000
0"
#6200000
b1000000010000000 @
1"
#6220000
0"
#6240000
b1001001101100000 @
1"
#6260000
0"
#6280000
b1010011001000000 @
1"
#6300000
0"
#6320000
b1011100100100000 @
1"
#6340000
0"
#6360000
b1100110000000000 @
1"
#6380000
0"
#6400000
b1101111011100000 @
1"
#6420000
0"
#6440000
b1111000111000000 @
1"
#6460000
0"
#6480000
1,
b10000010010100000 @
1"
#6500000
0"
#6520000
0,
b11 3
b1011110000000 @
1"
#6540000
0"
#6560000
b10101001100000 @
1"
#6580000
0"
#6600000
b11110101000000 @
1"
#6620000
0"
#6640000
b101000000100000 @
1"
#6660000
0"
#6680000
b110001100000000 @
1"
#6700000
0"
#6720000
b111010111100000 @
1"
#6740000
0"
#6760000
b1000100011000000 @
1"
#6780000
0"
#6800000
b1001101110100000 @
1"
#6820000
0"
#6840000
b1010111010000000 @
1"
#6860000
0"
#6880000
b1100000101100000 @
1"
#6900000
0"
#6920000
b1101010001000000 @
1"
#6940000
0"
#6960000
b1110011100100000 @
1"
#6980000
0"
#7000000
b1111101000000000 @
1"
#7020000
0"
#7040000
1,
b10000110011100000 @
1"
#7060000
0"
#7080000
0,
b100 3
b1111111000000 @
1"
#7100000
0"
#7120000
b11001010100000 @
1"
#7140000
0"
#7160000
b100010110000000 @
1"
#7180000
0"
#7200000
b101100001100000 @
1"
#7220000
0"
#7240000
b110101101000000 @
1"
#7260000
0"
#7280000
b111111000100000 @
1"
#7300000
0"
#7320000
b1001000100000000 @
1"
#7340000
0"
#7360000
b1010001111100000 @
1"
#7380000
0"
#7400000
b1011011011000000 @
1"
#7420000
0"
#7440000
b1100100110100000 @
1"
#7460000
0"
#7480000
b1101110010000000 @
1"
#7500000
0"
#7520000
b1110111101100000 @
1"
#7540000
0"
#7560000
1,
b10000001001000000 @
1"
#7580000
0"
#7600000
0,
b1010100100000 @
b101 3
1"
#7620000
0"
#7640000
b10100000000000 @
1"
#7660000
0"
#7680000
b11101011100000 @
1"
#7700000
0"
#7720000
b100110111000000 @
1"
#7740000
0"
#7760000
b110000010100000 @
1"
#7780000
0"
#7800000
b111001110000000 @
1"
#7820000
0"
#7840000
b1000011001100000 @
1"
#7860000
0"
#7880000
b1001100101000000 @
1"
#7900000
0"
#7920000
b1010110000100000 @
1"
#7940000
0"
#7960000
b1011111100000000 @
1"
#7980000
0"
#8000000
b1101000111100000 @
1"
#8020000
0"
#8040000
b1110010011000000 @
1"
#8060000
0"
#8080000
b1111011110100000 @
1"
#8100000
0"
#8120000
1,
b10000101010000000 @
1"
#8140000
0"
#8160000
0,
b1110101100000 @
b110 3
1"
#8180000
0"
#8200000
b11000001000000 @
1"
#8220000
0"
#8240000
b100001100100000 @
1"
#8260000
0"
#8280000
b101011000000000 @
1"
#8300000
0"
#8320000
b110100011100000 @
1"
#8340000
0"
#8360000
b111101111000000 @
1"
#8380000
0"
#8400000
b1000111010100000 @
1"
#8420000
0"
#8440000
b1010000110000000 @
1"
#8460000
0"
#8480000
b1011010001100000 @
1"
#8500000
0"
#8520000
b1100011101000000 @
1"
#8540000
0"
#8560000
b1101101000100000 @
1"
#8580000
0"
#8600000
b1110110100000000 @
1"
#8620000
0"
#8640000
b1111111111100000 @
1"
#8660000
0"
#8680000
1,
b10001001011000000 @
1"
#8700000
0"
#8720000
0,
b10010110100000 @
b111 3
1"
#8740000
0"
#8760000
b11100010000000 @
1"
#8780000
0"
#8800000
b100101101100000 @
1"
#8820000
0"
#8840000
b101111001000000 @
1"
#8860000
0"
#8880000
b111000100100000 @
1"
#8900000
0"
#8920000
b1000010000000000 @
1"
#8940000
0"
#8960000
b1001011011100000 @
1"
#8980000
0"
#9000000
b1010100111000000 @
1"
#9020000
0"
#9040000
b1011110010100000 @
1"
#9060000
0"
#9080000
b1100111110000000 @
1"
#9100000
0"
#9120000
b1110001001100000 @
1"
#9140000
0"
#9160000
b1111010101000000 @
1"
#9180000
0"
#9200000
1,
b10000100000100000 @
1"
#9220000
0"
#9240000
0,
b1000 3
b1101100000000 @
1"
#9260000
0"
#9280000
b10110111100000 @
1"
#9300000
0"
#9320000
b100000011000000 @
1"
#9340000
0"
#9360000
b101001110100000 @
1"
#9380000
0"
#9400000
b110011010000000 @
1"
#9420000
0"
#9440000
b111100101100000 @
1"
#9460000
0"
#9480000
b1000110001000000 @
1"
#9500000
0"
#9520000
b1001111100100000 @
1"
#9540000
0"
#9560000
b1011001000000000 @
1"
#9580000
0"
#9600000
b1100010011100000 @
1"
#9620000
0"
#9640000
b1101011111000000 @
1"
#9660000
0"
#9680000
b1110101010100000 @
1"
#9700000
0"
#9720000
b1111110110000000 @
1"
#9740000
0"
#9760000
1+
1,
b10001000001100000 @
1"
#9780000
0"
#9800000
0+
0,
b1000 6
b1001 3
b10001101000000 @
1"
#9820000
0"
#9840000
b11011000100000 @
1"
#9860000
0"
#9880000
b100100100000000 @
1"
#9900000
0"
#9920000
b101101111100000 @
1"
#9940000
0"
#9960000
b110111011000000 @
1"
#9980000
0"
#10000000
b1000000110100000 @
1"
#10020000
0"
#10040000
b1001010010000000 @
1"
#10060000
0"
#10080000
b1010011101100000 @
1"
#10100000
0"
#10120000
b1011101001000000 @
1"
#10140000
0"
#10160000
b1100110100100000 @
1"
#10180000
0"
#10200000
b1110000000000000 @
1"
#10220000
0"
#10240000
b1111001011100000 @
1"
#10260000
0"
#10280000
1,
b10000010111000000 @
1"
#10300000
0"
#10320000
0,
b1100010100000 @
b1010 3
1"
#10340000
0"
#10360000
b10101110000000 @
1"
#10380000
0"
#10400000
b11111001100000 @
1"
#10420000
0"
#10440000
b101000101000000 @
1"
#10460000
0"
#10480000
b110010000100000 @
1"
#10500000
0"
#10520000
b111011100000000 @
1"
#10540000
0"
#10560000
b1000100111100000 @
1"
#10580000
0"
#10600000
b1001110011000000 @
1"
#10620000
0"
#10640000
b1010111110100000 @
1"
#10660000
0"
#10680000
b1100001010000000 @
1"
1!
#10700000
0"
#10720000
b1101010101100000 @
1"
#10740000
0"
#10760000
b1110100001000000 @
1"
#10780000
0"
#10800000
b1111101100100000 @
1"
#10820000
0"
#10840000
1,
b10000111000000000 @
1"
#10860000
0"
#10880000
0,
b10000011100000 @
b1 7
b1011 3
1"
#10900000
0"
#10920000
b11001111000000 @
1"
#10940000
0"
#10960000
b100011010100000 @
1"
#10980000
0"
#11000000
b101100110000000 @
1"
#11020000
0"
#11040000
b110110001100000 @
1"
#11060000
0"
#11080000
b111111101000000 @
1"
#11100000
0"
#11120000
b1001001000100000 @
1"
#11140000
0"
#11160000
b1010010100000000 @
1"
#11180000
0"
#11200000
b1011011111100000 @
1"
#11220000
0"
#11240000
b1100101011000000 @
1"
#11260000
0"
#11280000
b1101110110100000 @
1"
#11300000
0"
#11320000
b1111000010000000 @
1"
#11340000
0"
#11360000
1,
b10000001101100000 @
1"
#11380000
0"
#11400000
0,
b1100 3
b11 7
b1011001000000 @
1"
#11420000
0"
#11440000
b10100100100000 @
1"
#11460000
0"
#11480000
b11110000000000 @
1"
#11500000
0"
#11520000
b100111011100000 @
1"
#11540000
0"
#11560000
b110000111000000 @
1"
#11580000
0"
#11600000
b111010010100000 @
1"
#11620000
0"
#11640000
b1000011110000000 @
1"
#11660000
0"
#11680000
b1001101001100000 @
1"
#11700000
0"
#11720000
b1010110101000000 @
1"
#11740000
0"
#11760000
b1100000000100000 @
1"
#11780000
0"
#11800000
b1101001100000000 @
1"
#11820000
0"
#11840000
b1110010111100000 @
1"
#11860000
0"
#11880000
b1111100011000000 @
1"
#11900000
0"
#11920000
1,
b10000101110100000 @
1"
#11940000
0"
#11960000
0,
b1101 3
b1 1
b1111010000000 @
1"
#11980000
0"
#12000000
b11000101100000 @
1"
#12020000
0"
#12040000
b100010001000000 @
1"
#12060000
0"
#12080000
b101011100100000 @
1"
#12100000
0"
#12120000
b110101000000000 @
1"
#12140000
0"
#12160000
b111110011100000 @
1"
#12180000
0"
#12200000
b1000111111000000 @
1"
#12220000
0"
#12240000
b1010001010100000 @
1"
#12260000
0"
#12280000
b1011010110000000 @
1"
#12300000
0"
#12320000
b1100100001100000 @
1"
#12340000
0"
#12360000
b1101101101000000 @
1"
#12380000
0"
#12400000
b1110111000100000 @
1"
#12420000
0"
#12440000
1,
b10000000100000000 @
1"
#12460000
0"
#12480000
0,
b1001111100000 @
b10 1
b1110 3
1"
#12500000
0"
#12520000
b10011011000000 @
1"
#12540000
0"
#12560000
b11100110100000 @
1"
#12580000
0"
#12600000
b100110010000000 @
1"
#12620000
0"
#12640000
b101111101100000 @
1"
#12660000
0"
#12680000
b111001001000000 @
1"
#12700000
0"
#12720000
b1000010100100000 @
1"
#12740000
0"
#12760000
b1001100000000000 @
1"
#12780000
0"
#12800000
b1010101011100000 @
1"
#12820000
0"
#12840000
b1011110111000000 @
1"
#12860000
0"
#12880000
b1101000010100000 @
1"
#12900000
0"
#12920000
b1110001110000000 @
1"
#12940000
0"
#12960000
b1111011001100000 @
1"
#12980000
0"
#13000000
1,
b10000100101000000 @
1"
#13020000
0"
#13040000
0,
b1110000100000 @
b11 1
b1111 3
1"
#13060000
0"
#13080000
b10111100000000 @
1"
#13100000
0"
#13120000
b100000111100000 @
1"
#13140000
0"
#13160000
b101010011000000 @
1"
#13180000
0"
#13200000
b110011110100000 @
1"
#13220000
0"
#13240000
b111101010000000 @
1"
#13260000
0"
#13280000
b1000110101100000 @
1"
#13300000
0"
#13320000
b1010000001000000 @
1"
#13340000
0"
#13360000
b1011001100100000 @
1"
#13380000
0"
#13400000
b1100011000000000 @
1"
#13420000
0"
#13440000
b1101100011100000 @
1"
#13460000
0"
#13480000
b1110101111000000 @
1"
#13500000
0"
#13520000
b1111111010100000 @
1"
#13540000
0"
#13560000
1,
b10001000110000000 @
1"
#13580000
0"
#13600000
0,
b10010001100000 @
14
b0 3
1"
#13620000
0"
#13640000
b11011101000000 @
1"
#13660000
0"
#13680000
b100101000100000 @
1"
#13700000
0"
#13720000
b101110100000000 @
1"
#13740000
0"
#13760000
b110111111100000 @
1"
#13780000
0"
#13800000
b1000001011000000 @
1"
#13820000
0"
#13840000
b1001010110100000 @
1"
#13860000
0"
#13880000
b1010100010000000 @
1"
#13900000
0"
#13920000
b1011101101100000 @
1"
#13940000
0"
#13960000
b1100111001000000 @
1"
#13980000
0"
#14000000
b1110000100100000 @
1"
#14020000
0"
#14040000
b1111010000000000 @
1"
#14060000
0"
#14080000
1,
b10000011011100000 @
1"
#14100000
0"
#14120000
0,
b1 3
b1100111000000 @
1"
#14140000
0"
#14160000
b10110010100000 @
1"
#14180000
0"
#14200000
b11111110000000 @
1"
#14220000
0"
#14240000
b101001001100000 @
1"
#14260000
0"
#14280000
b110010101000000 @
1"
#14300000
0"
#14320000
b111100000100000 @
1"
#14340000
0"
#14360000
b1000101100000000 @
1"
#14380000
0"
#14400000
b1001110111100000 @
1"
#14420000
0"
#14440000
b1011000011000000 @
1"
#14460000
0"
#14480000
b1100001110100000 @
1"
#14500000
0"
#14520000
b1101011010000000 @
1"
#14540000
0"
#14560000
b1110100101100000 @
1"
#14580000
0"
#14600000
b1111110001000000 @
1"
#14620000
0"
#14640000
1,
b10000111100100000 @
1"
#14660000
0"
#14680000
0,
b10 3
b10001000000000 @
1"
#14700000
0"
#14720000
b11010011100000 @
1"
#14740000
0"
#14760000
b100011111000000 @
1"
#14780000
0"
#14800000
b101101010100000 @
1"
#14820000
0"
#14840000
b110110110000000 @
1"
#14860000
0"
#14880000
b1000000001100000 @
1"
#14900000
0"
#14920000
b1001001101000000 @
1"
#14940000
0"
#14960000
b1010011000100000 @
1"
#14980000
0"
#15000000
b1011100100000000 @
1"
#15020000
0"
#15040000
b1100101111100000 @
1"
#15060000
0"
#15080000
b1101111011000000 @
1"
#15100000
0"
#15120000
b1111000110100000 @
1"
#15140000
0"
#15160000
1,
b10000010010000000 @
1"
#15180000
0"
#15200000
0,
b1011101100000 @
b11 3
1"
#15220000
0"
#15240000
b10101001000000 @
1"
#15260000
0"
#15280000
b11110100100000 @
1"
#15300000
0"
#15320000
b101000000000000 @
1"
#15340000
0"
#15360000
b110001011100000 @
1"
#15380000
0"
#15400000
b111010111000000 @
1"
#15420000
0"
#15440000
b1000100010100000 @
1"
#15460000
0"
#15480000
b1001101110000000 @
1"
#15500000
0"
#15520000
b1010111001100000 @
1"
#15540000
0"
#15560000
b1100000101000000 @
1"
#15580000
0"
#15600000
b1101010000100000 @
1"
#15620000
0"
#15640000
b1110011100000000 @
1"
#15660000
0"
#15680000
b1111100111100000 @
1"
#15700000
0"
#15720000
1,
b10000110011000000 @
1"
#15740000
0"
#15760000
0,
b1111110100000 @
b100 3
1"
#15780000
0"
#15800000
b11001010000000 @
1"
#15820000
0"
#15840000
b100010101100000 @
1"
#15860000
0"
#15880000
b101100001000000 @
1"
#15900000
0"
#15920000
b110101100100000 @
1"
#15940000
0"
#15960000
b111111000000000 @
1"
#15980000
0"
#16000000
b1001000011100000 @
1"
#16020000
0"
#16040000
b1010001111000000 @
1"
#16060000
0"
#16080000
b1011011010100000 @
1"
#16100000
0"
#16120000
b1100100110000000 @
1"
#16140000
0"
#16160000
b1101110001100000 @
1"
#16180000
0"
#16200000
b1110111101000000 @
1"
#16220000
0"
#16240000
1,
b10000001000100000 @
1"
#16260000
0"
