98SkillTest2Prep/Skiltest_2025/skilltest2_to_student/P1/lfsr_16.v
module lfsr_16 (
    input wire clk,
    input wire reset,
    input wire enable,
    output reg [15:0] lfsr_out
);

  always @(posedge clk ) begin
    if (reset) begin
      lfsr_out =  16'hFFFF;
    end else if (enable) begin
      lfsr_out = {lfsr_out[14:0], (lfsr_out[3] ^ lfsr_out[12]) ^ (lfsr_out[14] ^ lfsr_out[15])};
    end
  end

`ifdef COCOTB_SIM
  initial begin
    $dumpfile("waveform.vcd");  // Name of the dump file
    $dumpvars(0, lfsr_16);  // Dump all variables for the top module
  end
`endif

endmodule

98SkillTest2Prep/Skiltest_2025/skilltest2_to_student/P1/cocotb/waveform.vcd
$date
	Thu Apr 09 13:05:05 2026
$end
$version
	Icarus Verilog
$end
$timescale
	1ps
$end
$scope module lfsr_16 $end
$var wire 1 ! clk $end
$var wire 1 " enable $end
$var wire 1 # reset $end
$var reg 16 $ lfsr_out [15:0] $end
$upscope $end
$enddefinitions $end
$comment Show the parameter values. $end
$dumpall
$end
#0
$dumpvars
b1111111111111111 $
1#
0"
1!
$end
#5000
0!
#10000
1!
0#
#15000
0!
#20000
1!
#25000
0!
#30000
1!
#35000
0!
#40000
1!
#45000
0!
#50000
1!
#55000
0!
#60000
1!
#65000
0!
#70001
1!
1#
#75001
0!
#80001
b1111111111111110 $
1!
1"
0#
#85001
0!
#90001
1!
0"
#95001
0!
#100001
b1111111111111100 $
1!
1"
#105001
0!
#110001
1!
0"
#115001
0!
#120001
b1111111111111000 $
1!
1"
#125001
0!
#130001
1!
0"
#135001
0!
#140001
b1111111111110000 $
1!
1"
#145001
0!
#150001
1!
0"
#155001
0!
#160001
b1111111111100001 $
1!
1"
#165001
0!
#170001
1!
0"
#175001
0!
#180001
b1111111111000011 $
1!
1"
#185001
0!
#190001
1!
0"
#195001
0!
#200001
b1111111110000111 $
1!
1"
#205001
0!
#210001
1!
0"
#215001
0!
#220001
b1111111100001111 $
1!
1"
#225001
0!
#230001
1!
0"
#235001
0!
#240001
b1111111000011110 $
1!
1"
#245001
0!
#250001
1!
0"
#255001
0!
#260001
b1111110000111100 $
1!
1"
#265001
0!
#270001
1!
0"
#275001
0!
#280001
b1111100001111000 $
1!
1"
#285001
0!
#290001
1!
0"
#295001
0!
#300001
b1111000011110000 $
1!
1"
#305001
0!
#310001
1!
0"
#315001
0!
#320001
b1110000111100001 $
1!
1"
#325001
0!
#330001
1!
0"
#335001
0!
#340001
b1100001111000010 $
1!
1"
#345001
0!
#350001
1!
0"
#355001
0!
#360001
b1000011110000100 $
1!
1"
#365001
0!
#370001
1!
0"
#375001
0!
#380001
b111100001001 $
1!
1"
#385001
0!
#390001
1!
0"
