03lab3/part3/problem-2/fsm.v
module fsm (
    input  wire       clk,
    input  wire       rst,
    input  wire       data_in,
    output reg  [1:0] data_out
);

    localparam A = 2'b00;
    localparam B = 2'b01;
    localparam C = 2'b10;
    localparam D = 2'b11;

    reg [1:0] state;

    always @(state) begin
        case (state)
            A: data_out <= 2'b01;
            B: data_out <= 2'b11;
            C: data_out <= 2'b00;
            D: data_out <= 2'b10;
            default: data_out <= 2'b00;
        endcase
    end

    always @(posedge clk) begin
        if (rst) state <= A;
        else begin
            case (state)
                A: state <= (data_in == 1'b1) ? B : D;
                B: state <= (data_in == 1'b1) ? C : D;
                C: state <= (data_in == 1'b1) ? B : D;
                D: state <= (data_in == 1'b1) ? B : A;
                default: state <= A;
            endcase
        end
    end

endmodule

03lab3/part3/problem-2/fsm_tb.v
`timescale 1ns / 1ns

module fsm_tb ();
    // Create wires and regs to connect to the DUT
    reg        clk;
    reg        reset;
    reg        data_in;
    wire [1:0] data_out;

    // TODO: instantiate the DUT and write the testbench logic
    fsm dut (
        .clk (clk),
        .rst (reset),
        .data_in (data_in),
        .data_out (data_out)
    );

    initial begin
        clk = 0;
        forever #5 clk = ~clk;
    end

    initial begin
        $monitor("Time = %2t | reset = %b | data_in = %b | data_out = %b"
                , $time, reset, data_in, data_out);
    end

    initial begin
        data_in = 0;
        reset = 1;
        #10;
        reset = 0;
        $display("--- Simulation Start ---");

        // Current State: A (Output 01)
        check_transition(1, 2'b11, "A -> B");
        check_transition(1, 2'b00, "B -> C");
        check_transition(1, 2'b11, "C -> B");
        check_transition(0, 2'b10, "B -> D");
        check_transition(1, 2'b11, "D -> B");

        // Reset path manually to get to C
        @(negedge clk) data_in = 1; // B -> C
        @(posedge clk) #1;
        $display("State Reset to C manually...");

        check_transition(0, 2'b10, "C -> D");
        check_transition(0, 2'b01, "D -> A");
        check_transition(0, 2'b10, "A -> D");

        // Add delay to see final state in waveform
        #10;
        $display("--- Test Passed ---");
        $finish;
    end

    task check_transition;
        input       i_val;
        input [1:0] expected_out;
        input [50*8:1] step_name;
        begin
            @(negedge clk);
            data_in = i_val;
            @(posedge clk);
            #1;
        end
    endtask

    // -- Do not delete the lines below --
    // Dump waveforms
    initial begin
        $dumpfile("fsm_tb.vcd");
        $dumpvars(0, fsm_tb);
    end

endmodule

03lab3/part3/part3_project/part3_project.sim/sim_1/behav/xsim/fsm_tb.vcd
$date
   Tue Jan 27 12:05:44 2026
$end

$version
  2025.2
  $dumpfile ("fsm_tb.vcd") 
$end

$timescale
  1ps
$end

$scope module fsm_tb $end
$var reg 1 ! clk $end
$var reg 1 " reset $end
$var reg 1 # data_in $end
$var wire 2 $ data_out [1:0] $end
$scope module dut $end
$var wire 1 % clk $end
$var wire 1 & rst $end
$var wire 1 ' data_in $end
$var reg 2 ( data_out [1:0] $end
$var reg 2 ) state [1:0] $end
$upscope $end
$scope task check_transition $end
$var reg 1 * i_val $end
$var reg 2 + expected_out [1:0] $end
$var reg 400 , step_name [399:0] $end
$upscope $end
$upscope $end
$enddefinitions $end

#0
$dumpvars
0!
1"
0#
bx $
0%
1&
0'
bx (
bx )
x*
bx +
bx ,
$end

#5000
1!
b1 $
1%
b1 (
b0 )

#10000
0!
0"
1#
0%
0&
1'
1*
b11 +
b10000010010000000101101001111100010000001000010 ,

#15000
1!
b11 $
1%
b11 (
b1 )

#16000
b0 +
b10000100010000000101101001111100010000001000011 ,

#20000
0!
0%

#25000
1!
b0 $
1%
b0 (
b10 )

#26000
b11 +
b10000110010000000101101001111100010000001000010 ,

#30000
0!
0%

#35000
1!
b11 $
1%
b11 (
b1 )

#36000
0*
b10 +
b10000100010000000101101001111100010000001000100 ,

#40000
0!
0#
0%
0'

#45000
1!
b10 $
1%
b10 (
b11 )

#46000
1*
b11 +
b10001000010000000101101001111100010000001000010 ,

#50000
0!
1#
0%
1'

#55000
1!
b11 $
1%
b11 (
b1 )

#60000
0!
0%

#65000
1!
b0 $
1%
b0 (
b10 )

#66000
0*
b10 +
b10000110010000000101101001111100010000001000100 ,

#70000
0!
0#
0%
0'

#75000
1!
b10 $
1%
b10 (
b11 )

#76000
b1 +
b10001000010000000101101001111100010000001000001 ,

#80000
0!
0%

#85000
1!
b1 $
1%
b1 (
b0 )

#86000
b10 +
b10000010010000000101101001111100010000001000100 ,

#90000
0!
0%

#95000
1!
b10 $
1%
b10 (
b11 )

#100000
0!
0%

#105000
1!
b1 $
1%
b1 (
b0 )
